robocrypt/__init__.py
robocrypt/__main__.py
robocrypt/cli.py
robocrypt/info.py
robocrypt/library.py
robocrypt-4.2.6.dist-info/LICENSE
robocrypt-4.2.6.dist-info/METADATA
robocrypt-4.2.6.dist-info/WHEEL
robocrypt-4.2.6.dist-info/entry_points.txt
robocrypt-4.2.6.dist-info/top_level.txt
robocrypt-4.2.6.dist-info/RECORD
