Metadata-Version: 2.1
Name: robocrypt
Version: 4.2.6
Summary: Simple encryption library that handles the background details for you.
Home-page: https://github.com/noahbroyles/Robocrypt
Author: Noah Broyles
Author-email: noah@x3nzpouwu.com
License: MIT
Platform: UNKNOWN
Classifier: License :: OSI Approved :: MIT License
Classifier: Programming Language :: Python :: 3
License-File: LICENSE
Requires-Dist: cryptography (>=3.4)
